temp_optimize/__init__.py
temp_optimize/core.py
temp_optimize/log.py
temp_optimize/utils.py
temp_optimize/server/__init__.py
temp_optimize/server/__main__.py
temp_optimize/server/mcp/__init__.py
temp_optimize/server/mcp/content.py
temp_optimize/server/mcp/math.py
temp_optimize/server/mcp/resource.py
temp_optimize/server/mcp/weather.py
temp_optimize/server/models/__init__.py
temp_optimize/server/models/models.py
temp_optimize/server/utils/__init__.py
temp_optimize/server/utils/auth_backends.py
temp_optimize/server/utils/database.py
temp_optimize/server/utils/user_manager.py
temp_optimize-0.1.3.dist-info/METADATA
temp_optimize-0.1.3.dist-info/WHEEL
temp_optimize-0.1.3.dist-info/top_level.txt
temp_optimize-0.1.3.dist-info/RECORD
